Metadata-Version: 1.0
Name: gooseftp
Version: 1.0.0
Summary: CLI Ftp-client
Home-page: UNKNOWN
Author: UNKNOWN
Author-email: zaviryukha.igor99@gmail.com
License: UNKNOWN
Platform: UNKNOWN
